simplemem/__init__.py
simplemem/__version__.py
simplemem/py.typed
simplemem/system.py
simplemem/config/__init__.py
simplemem/core/__init__.py
simplemem/core/answer_generator.py
simplemem/core/hybrid_retriever.py
simplemem/core/memory_builder.py
simplemem/database/__init__.py
simplemem/database/vector_store.py
simplemem/models/__init__.py
simplemem/models/memory_entry.py
simplemem/utils/__init__.py
simplemem/utils/embedding.py
simplemem/utils/llm_client.py
simplemem-0.1.0.dist-info/LICENSE
simplemem-0.1.0.dist-info/METADATA
simplemem-0.1.0.dist-info/WHEEL
simplemem-0.1.0.dist-info/top_level.txt
simplemem-0.1.0.dist-info/RECORD
