Metadata-Version: 2.1
Name: simplemem
Version: 0.1.0
Summary: Efficient Lifelong Memory for LLM Agents
Author: AIMING Lab, Jiaqi Liu
License: MIT
Project-URL: Homepage, https://github.com/aiming-lab/SimpleMem
Project-URL: Documentation, https://aiming-lab.github.io/SimpleMem-Page
Project-URL: Repository, https://github.com/aiming-lab/SimpleMem
Project-URL: Issues, https://github.com/aiming-lab/SimpleMem/issues
Project-URL: Paper, https://arxiv.org/abs/2601.02553
Keywords: llm,memory,agent,retrieval,vector-database,semantic-search,rag,langchain,openai
Classifier: Development Status :: 4 - Beta
Classifier: Intended Audience :: Developers
Classifier: Intended Audience :: Science/Research
Classifier: License :: OSI Approved :: MIT License
Classifier: Operating System :: OS Independent
Classifier: Programming Language :: Python :: 3
Classifier: Programming Language :: Python :: 3.10
Classifier: Programming Language :: Python :: 3.11
Classifier: Programming Language :: Python :: 3.12
Classifier: Topic :: Scientific/Engineering :: Artificial Intelligence
Classifier: Topic :: Software Development :: Libraries :: Python Modules
Requires-Python: >=3.10
License-File: LICENSE
Requires-Dist: openai>=1.0.0
Requires-Dist: pydantic>=2.0.0
Requires-Dist: lancedb>=0.4.0
Requires-Dist: sentence-transformers>=2.2.0
Requires-Dist: numpy>=1.24.0
Requires-Dist: dateparser>=1.1.0
Requires-Dist: pyarrow>=12.0.0
Requires-Dist: tantivy>=0.20.0
Provides-Extra: all
Requires-Dist: simplemem[benchmark,dev,gpu]; extra == "all"
Provides-Extra: benchmark
Requires-Dist: datasets>=2.0.0; extra == "benchmark"
Requires-Dist: bert-score>=0.3.0; extra == "benchmark"
Requires-Dist: rouge-score>=0.1.0; extra == "benchmark"
Provides-Extra: dev
Requires-Dist: pytest>=7.0.0; extra == "dev"
Requires-Dist: pytest-cov>=4.0.0; extra == "dev"
Requires-Dist: black>=23.0.0; extra == "dev"
Requires-Dist: ruff>=0.1.0; extra == "dev"
Requires-Dist: mypy>=1.0.0; extra == "dev"
Requires-Dist: build>=1.0.0; extra == "dev"
Requires-Dist: twine>=4.0.0; extra == "dev"
Provides-Extra: gpu
Requires-Dist: torch>=2.0.0; extra == "gpu"
